fortnitepyfix/__init__.py
fortnitepyfix/auth.py
fortnitepyfix/avatar.py
fortnitepyfix/client.py
fortnitepyfix/enums.py
fortnitepyfix/errors.py
fortnitepyfix/friend.py
fortnitepyfix/http.py
fortnitepyfix/message.py
fortnitepyfix/news.py
fortnitepyfix/party.py
fortnitepyfix/playlist.py
fortnitepyfix/presence.py
fortnitepyfix/stats.py
fortnitepyfix/store.py
fortnitepyfix/typedefs.py
fortnitepyfix/user.py
fortnitepyfix/utils.py
fortnitepyfix/xmpp.py
fortnitepyfix/ext/commands/__init__.py
fortnitepyfix/ext/commands/_types.py
fortnitepyfix/ext/commands/bot.py
fortnitepyfix/ext/commands/cog.py
fortnitepyfix/ext/commands/context.py
fortnitepyfix/ext/commands/converter.py
fortnitepyfix/ext/commands/cooldown.py
fortnitepyfix/ext/commands/core.py
fortnitepyfix/ext/commands/errors.py
fortnitepyfix/ext/commands/help.py
fortnitepyfix/ext/commands/typedefs.py
fortnitepyfix/ext/commands/view.py
fortnitepyfix-1.7.0.dist-info/METADATA
fortnitepyfix-1.7.0.dist-info/WHEEL
fortnitepyfix-1.7.0.dist-info/top_level.txt
fortnitepyfix-1.7.0.dist-info/RECORD
