Metadata-Version: 2.1
Name: fortnitepyfix
Version: 1.7.0
Summary: fortnitepyfix
Home-page: https://github.com/Terbau/fortnitepy
Author: klld
License: MIT
Project-URL: Documentation, https://fortnitepy.readthedocs.io/en/latest/
Project-URL: Issue tracker, https://github.com/Terbau/fortnitepy/issues
Classifier: License :: OSI Approved :: MIT License
Classifier: Intended Audience :: Developers
Classifier: Natural Language :: English
Classifier: Operating System :: OS Independent
Classifier: Programming Language :: Python :: 3.5
Classifier: Programming Language :: Python :: 3.6
Classifier: Programming Language :: Python :: 3.7
Classifier: Programming Language :: Python :: 3.8
Classifier: Programming Language :: Python :: 3.9
Classifier: Programming Language :: Python :: 3.10
Classifier: Topic :: Internet
Classifier: Topic :: Software Development :: Libraries
Classifier: Topic :: Software Development :: Libraries :: Python Modules
Classifier: Topic :: Utilities
Requires-Dist: sphinxcontrib-trio (==1.1.2)
Requires-Dist: furo (==2021.4.11b34)
Requires-Dist: Jinja2 (<3.1)
Requires-Dist: aiohttp (>=3.3)
Requires-Dist: aioxmpp (>=0.10.4)
Requires-Dist: pytz
Requires-Dist: aioconsole
Provides-Extra: docs
Requires-Dist: sphinxcontrib-trio (==1.1.2) ; extra == 'docs'
Requires-Dist: furo (==2021.4.11b34) ; extra == 'docs'
Requires-Dist: Jinja2 (<3.1) ; extra == 'docs'
